backports.statistics-0.1.0-py2.7-nspkg.pth
backports.statistics-0.1.0.dist-info/metadata.json
backports.statistics-0.1.0.dist-info/WHEEL
backports.statistics-0.1.0.dist-info/top_level.txt
backports.statistics-0.1.0.dist-info/METADATA
backports.statistics-0.1.0.dist-info/DESCRIPTION.rst
backports.statistics-0.1.0.dist-info/RECORD
backports.statistics-0.1.0.dist-info/namespace_packages.txt
backports/statistics/_counter.py
backports/statistics/__init__.py
